Workbook

Sheet Платформа
A1: MainExperts · P&L · Платформа (Поток-2, самообслуживание) · ₽ · белое — ввод, серое — авто
D2: июл.26 | G2: авг.26 | J2: сен.26 | M2: окт.26 | P2: ноя.26 | S2: дек.26 | V2: Год
A3: Код | B3: Статья / метрика | C3: Направление | D3: План | E3: Факт | F3: % | G3: План | H3: Факт | I3: % | J3: План | K3: Факт | L3: % | M3: План | N3: Факт | O3: % | P3: План | Q3: Факт | R3: % | S3: План | T3: Факт | U3: % | V3: План | W3: Факт | X3: %
B4: Трафик (визиты) | C4: маркетинг | V4: =IFERROR(D4+G4+J4+M4+P4+S4,"") | W4: =IFERROR(E4+H4+K4+N4+Q4+T4,"")
B5: Конверсия из визита в оплату | C5: маркетинг | D5: =IFERROR(D7/D4,"") | E5: =IFERROR(E7/E4,"") | G5: =IFERROR(G7/G4,"") | H5: =IFERROR(H7/H4,"") | J5: =IFERROR(J7/J4,"") | K5: =IFERROR(K7/K4,"") | M5: =IFERROR(M7/M4,"") | N5: =IFERROR(N7/N4,"") | P5: =IFERROR(P7/P4,"") | Q5: =IFERROR(Q7/Q4,"") | S5: =IFERROR(S7/S4,"") | T5: =IFERROR(T7/T4,"") | V5: =IFERROR(V7/V4,"") | W5: =IFERROR(W7/W4,"")
B6: CAC (стоимость привлечения) | C6: маркетинг | D6: =IFERROR(D12/D7,"") | E6: =IFERROR(E12/E7,"") | G6: =IFERROR(G12/G7,"") | H6: =IFERROR(H12/H7,"") | J6: =IFERROR(J12/J7,"") | K6: =IFERROR(K12/K7,"") | M6: =IFERROR(M12/M7,"") | N6: =IFERROR(N12/N7,"") | P6: =IFERROR(P12/P7,"") | Q6: =IFERROR(Q12/Q7,"") | S6: =IFERROR(S12/S7,"") | T6: =IFERROR(T12/T7,"") | V6: =IFERROR(V12/V7,"") | W6: =IFERROR(W12/W7,"")
B7: Кол-во оплат | C7: продажи | V7: =IFERROR(D7+G7+J7+M7+P7+S7,"") | W7: =IFERROR(E7+H7+K7+N7+Q7+T7,"")
B8: Средний чек | C8: продукт | D8: =IFERROR(D10/D7,"") | E8: =IFERROR(E10/E7,"") | G8: =IFERROR(G10/G7,"") | H8: =IFERROR(H10/H7,"") | J8: =IFERROR(J10/J7,"") | K8: =IFERROR(K10/K7,"") | M8: =IFERROR(M10/M7,"") | N8: =IFERROR(N10/N7,"") | P8: =IFERROR(P10/P7,"") | Q8: =IFERROR(Q10/Q7,"") | S8: =IFERROR(S10/S7,"") | T8: =IFERROR(T10/T7,"") | V8: =IFERROR(V10/V7,"") | W8: =IFERROR(W10/W7,"")
B9: Выручка по оплатам | C9: финансы | V9: =IFERROR(D9+G9+J9+M9+P9+S9,"") | W9: =IFERROR(E9+H9+K9+N9+Q9+T9,"")
B10: Выручка всего | C10: финансы | D10: =IFERROR(D9,"") | E10: =IFERROR(E9,"") | F10: =IFERROR(E10/E10,"") | G10: =IFERROR(G9,"") | H10: =IFERROR(H9,"") | I10: =IFERROR(H10/H10,"") | J10: =IFERROR(J9,"") | K10: =IFERROR(K9,"") | L10: =IFERROR(K10/K10,"") | M10: =IFERROR(M9,"") | N10: =IFERROR(N9,"") | O10: =IFERROR(N10/N10,"") | P10: =IFERROR(P9,"") | Q10: =IFERROR(Q9,"") | R10: =IFERROR(Q10/Q10,"") | S10: =IFERROR(S9,"") | T10: =IFERROR(T9,"") | U10: =IFERROR(T10/T10,"") | V10: =IFERROR(V9,"") | W10: =IFERROR(W9,"") | X10: =IFERROR(W10/W10,"")
B11: Расходы всего | C11: финансы | D11: =IFERROR(SUM(D12:D18),"") | E11: =IFERROR(SUM(E12:E18),"") | F11: =IFERROR(E11/E10,"") | G11: =IFERROR(SUM(G12:G18),"") | H11: =IFERROR(SUM(H12:H18),"") | I11: =IFERROR(H11/H10,"") | J11: =IFERROR(SUM(J12:J18),"") | K11: =IFERROR(SUM(K12:K18),"") | L11: =IFERROR(K11/K10,"") | M11: =IFERROR(SUM(M12:M18),"") | N11: =IFERROR(SUM(N12:N18),"") | O11: =IFERROR(N11/N10,"") | P11: =IFERROR(SUM(P12:P18),"") | Q11: =IFERROR(SUM(Q12:Q18),"") | R11: =IFERROR(Q11/Q10,"") | S11: =IFERROR(SUM(S12:S18),"") | T11: =IFERROR(SUM(T12:T18),"") | U11: =IFERROR(T11/T10,"") | V11: =IFERROR(SUM(V12:V18),"") | W11: =IFERROR(SUM(W12:W18),"") | X11: =IFERROR(W11/W10,"")
A12: M | B12: Маркетинг РБ (рекламный бюджет) | C12: маркетинг | F12: =IFERROR(E12/E10,"") | I12: =IFERROR(H12/H10,"") | L12: =IFERROR(K12/K10,"") | O12: =IFERROR(N12/N10,"") | R12: =IFERROR(Q12/Q10,"") | U12: =IFERROR(T12/T10,"") | V12: =IFERROR(D12+G12+J12+M12+P12+S12,"") | W12: =IFERROR(E12+H12+K12+N12+Q12+T12,"") | X12: =IFERROR(W12/W10,"")
A13: M | B13: ФОТ Платформа (разработка, маркетинг, владелец, Саша, Вадим) | C13: операционка | F13: =IFERROR(E13/E10,"") | I13: =IFERROR(H13/H10,"") | L13: =IFERROR(K13/K10,"") | O13: =IFERROR(N13/N10,"") | R13: =IFERROR(Q13/Q10,"") | U13: =IFERROR(T13/T10,"") | V13: =IFERROR(D13+G13+J13+M13+P13+S13,"") | W13: =IFERROR(E13+H13+K13+N13+Q13+T13,"") | X13: =IFERROR(W13/W10,"")
A14: M | B14: Инструменты/Сервисы (GetCourse, хостинг, аналитика) | C14: маркетинг | F14: =IFERROR(E14/E10,"") | I14: =IFERROR(H14/H10,"") | L14: =IFERROR(K14/K10,"") | O14: =IFERROR(N14/N10,"") | R14: =IFERROR(Q14/Q10,"") | U14: =IFERROR(T14/T10,"") | V14: =IFERROR(D14+G14+J14+M14+P14+S14,"") | W14: =IFERROR(E14+H14+K14+N14+Q14+T14,"") | X14: =IFERROR(W14/W10,"")
A15: Pr | B15: AI-стоимость (генерация отчётов) | C15: разработка | F15: =IFERROR(E15/E10,"") | I15: =IFERROR(H15/H10,"") | L15: =IFERROR(K15/K10,"") | O15: =IFERROR(N15/N10,"") | R15: =IFERROR(Q15/Q10,"") | U15: =IFERROR(T15/T10,"") | V15: =IFERROR(D15+G15+J15+M15+P15+S15,"") | W15: =IFERROR(E15+H15+K15+N15+Q15+T15,"") | X15: =IFERROR(W15/W10,"")
A16: Pr | B16: Себестоимость (инфраструктура/хостинг перем.) | C16: разработка | F16: =IFERROR(E16/E10,"") | I16: =IFERROR(H16/H10,"") | L16: =IFERROR(K16/K10,"") | O16: =IFERROR(N16/N10,"") | R16: =IFERROR(Q16/Q10,"") | U16: =IFERROR(T16/T10,"") | V16: =IFERROR(D16+G16+J16+M16+P16+S16,"") | W16: =IFERROR(E16+H16+K16+N16+Q16+T16,"") | X16: =IFERROR(W16/W10,"")
A17: A | B17: Эквайринг (Робокасса 10%) | C17: финансы | D17: =IFERROR(D10*0.1,"") | E17: =IFERROR(E10*0.1,"") | F17: =IFERROR(E17/E10,"") | G17: =IFERROR(G10*0.1,"") | H17: =IFERROR(H10*0.1,"") | I17: =IFERROR(H17/H10,"") | J17: =IFERROR(J10*0.1,"") | K17: =IFERROR(K10*0.1,"") | L17: =IFERROR(K17/K10,"") | M17: =IFERROR(M10*0.1,"") | N17: =IFERROR(N10*0.1,"") | O17: =IFERROR(N17/N10,"") | P17: =IFERROR(P10*0.1,"") | Q17: =IFERROR(Q10*0.1,"") | R17: =IFERROR(Q17/Q10,"") | S17: =IFERROR(S10*0.1,"") | T17: =IFERROR(T10*0.1,"") | U17: =IFERROR(T17/T10,"") | V17: =IFERROR(V10*0.1,"") | W17: =IFERROR(W10*0.1,"") | X17: =IFERROR(W17/W10,"")
A18: A | B18: Административные | C18: финансы | F18: =IFERROR(E18/E10,"") | I18: =IFERROR(H18/H10,"") | L18: =IFERROR(K18/K10,"") | O18: =IFERROR(N18/N10,"") | R18: =IFERROR(Q18/Q10,"") | U18: =IFERROR(T18/T10,"") | V18: =IFERROR(D18+G18+J18+M18+P18+S18,"") | W18: =IFERROR(E18+H18+K18+N18+Q18+T18,"") | X18: =IFERROR(W18/W10,"")
B19: Маржинальная прибыль | C19: финансы | D19: =IFERROR(D10-D11,"") | E19: =IFERROR(E10-E11,"") | F19: =IFERROR(E19/E10,"") | G19: =IFERROR(G10-G11,"") | H19: =IFERROR(H10-H11,"") | I19: =IFERROR(H19/H10,"") | J19: =IFERROR(J10-J11,"") | K19: =IFERROR(K10-K11,"") | L19: =IFERROR(K19/K10,"") | M19: =IFERROR(M10-M11,"") | N19: =IFERROR(N10-N11,"") | O19: =IFERROR(N19/N10,"") | P19: =IFERROR(P10-P11,"") | Q19: =IFERROR(Q10-Q11,"") | R19: =IFERROR(Q19/Q10,"") | S19: =IFERROR(S10-S11,"") | T19: =IFERROR(T10-T11,"") | U19: =IFERROR(T19/T10,"") | V19: =IFERROR(V10-V11,"") | W19: =IFERROR(W10-W11,"") | X19: =IFERROR(W19/W10,"")
B20: Выручка с 1 оплаты | C20: финансы | D20: =IFERROR(D10/D7,"") | E20: =IFERROR(E10/E7,"") | G20: =IFERROR(G10/G7,"") | H20: =IFERROR(H10/H7,"") | J20: =IFERROR(J10/J7,"") | K20: =IFERROR(K10/K7,"") | M20: =IFERROR(M10/M7,"") | N20: =IFERROR(N10/N7,"") | P20: =IFERROR(P10/P7,"") | Q20: =IFERROR(Q10/Q7,"") | S20: =IFERROR(S10/S7,"") | T20: =IFERROR(T10/T7,"") | V20: =IFERROR(V10/V7,"") | W20: =IFERROR(W10/W7,"")
B21: Расходы на 1 оплату | C21: финансы | D21: =IFERROR(D11/D7,"") | E21: =IFERROR(E11/E7,"") | G21: =IFERROR(G11/G7,"") | H21: =IFERROR(H11/H7,"") | J21: =IFERROR(J11/J7,"") | K21: =IFERROR(K11/K7,"") | M21: =IFERROR(M11/M7,"") | N21: =IFERROR(N11/N7,"") | P21: =IFERROR(P11/P7,"") | Q21: =IFERROR(Q11/Q7,"") | S21: =IFERROR(S11/S7,"") | T21: =IFERROR(T11/T7,"") | V21: =IFERROR(V11/V7,"") | W21: =IFERROR(W11/W7,"")
B22: Маржинальная прибыль на 1 оплату | C22: финансы | D22: =IFERROR(D19/D7,"") | E22: =IFERROR(E19/E7,"") | G22: =IFERROR(G19/G7,"") | H22: =IFERROR(H19/H7,"") | J22: =IFERROR(J19/J7,"") | K22: =IFERROR(K19/K7,"") | M22: =IFERROR(M19/M7,"") | N22: =IFERROR(N19/N7,"") | P22: =IFERROR(P19/P7,"") | Q22: =IFERROR(Q19/Q7,"") | S22: =IFERROR(S19/S7,"") | T22: =IFERROR(T19/T7,"") | V22: =IFERROR(V19/V7,"") | W22: =IFERROR(W19/W7,"")
B23: Маржинальность оплаты | C23: финансы | D23: =IFERROR((D20-D21)/D20,"") | E23: =IFERROR((E20-E21)/E20,"") | G23: =IFERROR((G20-G21)/G20,"") | H23: =IFERROR((H20-H21)/H20,"") | J23: =IFERROR((J20-J21)/J20,"") | K23: =IFERROR((K20-K21)/K20,"") | M23: =IFERROR((M20-M21)/M20,"") | N23: =IFERROR((N20-N21)/N20,"") | P23: =IFERROR((P20-P21)/P20,"") | Q23: =IFERROR((Q20-Q21)/Q20,"") | S23: =IFERROR((S20-S21)/S20,"") | T23: =IFERROR((T20-T21)/T20,"") | V23: =IFERROR((V20-V21)/V20,"") | W23: =IFERROR((W20-W21)/W20,"")

Sheet Поток-1
A1: MainExperts · P&L · Поток-1 (агентство / личные продажи, 2 менеджера) · ₽ · белое — ввод, серое — авто
D2: июл.26 | G2: авг.26 | J2: сен.26 | M2: окт.26 | P2: ноя.26 | S2: дек.26 | V2: Год
A3: Код | B3: Статья / метрика | C3: Направление | D3: План | E3: Факт | F3: % | G3: План | H3: Факт | I3: % | J3: План | K3: Факт | L3: % | M3: План | N3: Факт | O3: % | P3: План | Q3: Факт | R3: % | S3: План | T3: Факт | U3: % | V3: План | W3: Факт | X3: %
B4: Кол-во входящих лидов | C4: продажи | V4: =IFERROR(D4+G4+J4+M4+P4+S4,"") | W4: =IFERROR(E4+H4+K4+N4+Q4+T4,"")
B5: Кол-во созвонов | C5: продажи | V5: =IFERROR(D5+G5+J5+M5+P5+S5,"") | W5: =IFERROR(E5+H5+K5+N5+Q5+T5,"")
B6: Конверсия лид→созвон | C6: продажи | D6: =IFERROR(D5/D4,"") | E6: =IFERROR(E5/E4,"") | G6: =IFERROR(G5/G4,"") | H6: =IFERROR(H5/H4,"") | J6: =IFERROR(J5/J4,"") | K6: =IFERROR(K5/K4,"") | M6: =IFERROR(M5/M4,"") | N6: =IFERROR(N5/N4,"") | P6: =IFERROR(P5/P4,"") | Q6: =IFERROR(Q5/Q4,"") | S6: =IFERROR(S5/S4,"") | T6: =IFERROR(T5/T4,"") | V6: =IFERROR(V5/V4,"") | W6: =IFERROR(W5/W4,"")
B7: Кол-во оплат | C7: продажи | V7: =IFERROR(D7+G7+J7+M7+P7+S7,"") | W7: =IFERROR(E7+H7+K7+N7+Q7+T7,"")
B8: Конверсия созвон→оплата | C8: продажи | D8: =IFERROR(D7/D5,"") | E8: =IFERROR(E7/E5,"") | G8: =IFERROR(G7/G5,"") | H8: =IFERROR(H7/H5,"") | J8: =IFERROR(J7/J5,"") | K8: =IFERROR(K7/K5,"") | M8: =IFERROR(M7/M5,"") | N8: =IFERROR(N7/N5,"") | P8: =IFERROR(P7/P5,"") | Q8: =IFERROR(Q7/Q5,"") | S8: =IFERROR(S7/S5,"") | T8: =IFERROR(T7/T5,"") | V8: =IFERROR(V7/V5,"") | W8: =IFERROR(W7/W5,"")
B9: Средний чек | C9: продажи | D9: =IFERROR(D10/D7,"") | E9: =IFERROR(E10/E7,"") | G9: =IFERROR(G10/G7,"") | H9: =IFERROR(H10/H7,"") | J9: =IFERROR(J10/J7,"") | K9: =IFERROR(K10/K7,"") | M9: =IFERROR(M10/M7,"") | N9: =IFERROR(N10/N7,"") | P9: =IFERROR(P10/P7,"") | Q9: =IFERROR(Q10/Q7,"") | S9: =IFERROR(S10/S7,"") | T9: =IFERROR(T10/T7,"") | V9: =IFERROR(V10/V7,"") | W9: =IFERROR(W10/W7,"")
B10: Сумма оплат (выручка) | C10: финансы | F10: =IFERROR(E10/E10,"") | I10: =IFERROR(H10/H10,"") | L10: =IFERROR(K10/K10,"") | O10: =IFERROR(N10/N10,"") | R10: =IFERROR(Q10/Q10,"") | U10: =IFERROR(T10/T10,"") | V10: =IFERROR(D10+G10+J10+M10+P10+S10,"") | W10: =IFERROR(E10+H10+K10+N10+Q10+T10,"") | X10: =IFERROR(W10/W10,"")
B11: Расходы всего | C11: финансы | D11: =IFERROR(SUM(D12:D17),"") | E11: =IFERROR(SUM(E12:E17),"") | F11: =IFERROR(E11/E10,"") | G11: =IFERROR(SUM(G12:G17),"") | H11: =IFERROR(SUM(H12:H17),"") | I11: =IFERROR(H11/H10,"") | J11: =IFERROR(SUM(J12:J17),"") | K11: =IFERROR(SUM(K12:K17),"") | L11: =IFERROR(K11/K10,"") | M11: =IFERROR(SUM(M12:M17),"") | N11: =IFERROR(SUM(N12:N17),"") | O11: =IFERROR(N11/N10,"") | P11: =IFERROR(SUM(P12:P17),"") | Q11: =IFERROR(SUM(Q12:Q17),"") | R11: =IFERROR(Q11/Q10,"") | S11: =IFERROR(SUM(S12:S17),"") | T11: =IFERROR(SUM(T12:T17),"") | U11: =IFERROR(T11/T10,"") | V11: =IFERROR(SUM(V12:V17),"") | W11: =IFERROR(SUM(W12:W17),"") | X11: =IFERROR(W11/W10,"")
A12: M | B12: Маркетинг / лидогенерация РБ | C12: маркетинг | F12: =IFERROR(E12/E10,"") | I12: =IFERROR(H12/H10,"") | L12: =IFERROR(K12/K10,"") | O12: =IFERROR(N12/N10,"") | R12: =IFERROR(Q12/Q10,"") | U12: =IFERROR(T12/T10,"") | V12: =IFERROR(D12+G12+J12+M12+P12+S12,"") | W12: =IFERROR(E12+H12+K12+N12+Q12+T12,"") | X12: =IFERROR(W12/W10,"")
A13: M | B13: ФОТ — Менеджер продаж 1 | C13: продажи | F13: =IFERROR(E13/E10,"") | I13: =IFERROR(H13/H10,"") | L13: =IFERROR(K13/K10,"") | O13: =IFERROR(N13/N10,"") | R13: =IFERROR(Q13/Q10,"") | U13: =IFERROR(T13/T10,"") | V13: =IFERROR(D13+G13+J13+M13+P13+S13,"") | W13: =IFERROR(E13+H13+K13+N13+Q13+T13,"") | X13: =IFERROR(W13/W10,"")
A14: M | B14: ФОТ — Менеджер продаж 2 | C14: продажи | F14: =IFERROR(E14/E10,"") | I14: =IFERROR(H14/H10,"") | L14: =IFERROR(K14/K10,"") | O14: =IFERROR(N14/N10,"") | R14: =IFERROR(Q14/Q10,"") | U14: =IFERROR(T14/T10,"") | V14: =IFERROR(D14+G14+J14+M14+P14+S14,"") | W14: =IFERROR(E14+H14+K14+N14+Q14+T14,"") | X14: =IFERROR(W14/W10,"")
A15: M | B15: Инструменты/Сервисы (CRM, телефония) | C15: продажи | F15: =IFERROR(E15/E10,"") | I15: =IFERROR(H15/H10,"") | L15: =IFERROR(K15/K10,"") | O15: =IFERROR(N15/N10,"") | R15: =IFERROR(Q15/Q10,"") | U15: =IFERROR(T15/T10,"") | V15: =IFERROR(D15+G15+J15+M15+P15+S15,"") | W15: =IFERROR(E15+H15+K15+N15+Q15+T15,"") | X15: =IFERROR(W15/W10,"")
A16: A | B16: Эквайринг (Робокасса 10%) | C16: финансы | D16: =IFERROR(D10*0.1,"") | E16: =IFERROR(E10*0.1,"") | F16: =IFERROR(E16/E10,"") | G16: =IFERROR(G10*0.1,"") | H16: =IFERROR(H10*0.1,"") | I16: =IFERROR(H16/H10,"") | J16: =IFERROR(J10*0.1,"") | K16: =IFERROR(K10*0.1,"") | L16: =IFERROR(K16/K10,"") | M16: =IFERROR(M10*0.1,"") | N16: =IFERROR(N10*0.1,"") | O16: =IFERROR(N16/N10,"") | P16: =IFERROR(P10*0.1,"") | Q16: =IFERROR(Q10*0.1,"") | R16: =IFERROR(Q16/Q10,"") | S16: =IFERROR(S10*0.1,"") | T16: =IFERROR(T10*0.1,"") | U16: =IFERROR(T16/T10,"") | V16: =IFERROR(V10*0.1,"") | W16: =IFERROR(W10*0.1,"") | X16: =IFERROR(W16/W10,"")
A17: A | B17: Административные | C17: финансы | F17: =IFERROR(E17/E10,"") | I17: =IFERROR(H17/H10,"") | L17: =IFERROR(K17/K10,"") | O17: =IFERROR(N17/N10,"") | R17: =IFERROR(Q17/Q10,"") | U17: =IFERROR(T17/T10,"") | V17: =IFERROR(D17+G17+J17+M17+P17+S17,"") | W17: =IFERROR(E17+H17+K17+N17+Q17+T17,"") | X17: =IFERROR(W17/W10,"")
B18: Маржинальная прибыль | C18: финансы | D18: =IFERROR(D10-D11,"") | E18: =IFERROR(E10-E11,"") | F18: =IFERROR(E18/E10,"") | G18: =IFERROR(G10-G11,"") | H18: =IFERROR(H10-H11,"") | I18: =IFERROR(H18/H10,"") | J18: =IFERROR(J10-J11,"") | K18: =IFERROR(K10-K11,"") | L18: =IFERROR(K18/K10,"") | M18: =IFERROR(M10-M11,"") | N18: =IFERROR(N10-N11,"") | O18: =IFERROR(N18/N10,"") | P18: =IFERROR(P10-P11,"") | Q18: =IFERROR(Q10-Q11,"") | R18: =IFERROR(Q18/Q10,"") | S18: =IFERROR(S10-S11,"") | T18: =IFERROR(T10-T11,"") | U18: =IFERROR(T18/T10,"") | V18: =IFERROR(V10-V11,"") | W18: =IFERROR(W10-W11,"") | X18: =IFERROR(W18/W10,"")
B19: Выручка с 1 оплаты | C19: финансы | D19: =IFERROR(D10/D7,"") | E19: =IFERROR(E10/E7,"") | G19: =IFERROR(G10/G7,"") | H19: =IFERROR(H10/H7,"") | J19: =IFERROR(J10/J7,"") | K19: =IFERROR(K10/K7,"") | M19: =IFERROR(M10/M7,"") | N19: =IFERROR(N10/N7,"") | P19: =IFERROR(P10/P7,"") | Q19: =IFERROR(Q10/Q7,"") | S19: =IFERROR(S10/S7,"") | T19: =IFERROR(T10/T7,"") | V19: =IFERROR(V10/V7,"") | W19: =IFERROR(W10/W7,"")
B20: Расходы на 1 оплату | C20: финансы | D20: =IFERROR(D11/D7,"") | E20: =IFERROR(E11/E7,"") | G20: =IFERROR(G11/G7,"") | H20: =IFERROR(H11/H7,"") | J20: =IFERROR(J11/J7,"") | K20: =IFERROR(K11/K7,"") | M20: =IFERROR(M11/M7,"") | N20: =IFERROR(N11/N7,"") | P20: =IFERROR(P11/P7,"") | Q20: =IFERROR(Q11/Q7,"") | S20: =IFERROR(S11/S7,"") | T20: =IFERROR(T11/T7,"") | V20: =IFERROR(V11/V7,"") | W20: =IFERROR(W11/W7,"")
B21: Маржинальная прибыль на 1 оплату | C21: финансы | D21: =IFERROR(D18/D7,"") | E21: =IFERROR(E18/E7,"") | G21: =IFERROR(G18/G7,"") | H21: =IFERROR(H18/H7,"") | J21: =IFERROR(J18/J7,"") | K21: =IFERROR(K18/K7,"") | M21: =IFERROR(M18/M7,"") | N21: =IFERROR(N18/N7,"") | P21: =IFERROR(P18/P7,"") | Q21: =IFERROR(Q18/Q7,"") | S21: =IFERROR(S18/S7,"") | T21: =IFERROR(T18/T7,"") | V21: =IFERROR(V18/V7,"") | W21: =IFERROR(W18/W7,"")
B22: Маржинальность оплаты | C22: финансы | D22: =IFERROR((D19-D20)/D19,"") | E22: =IFERROR((E19-E20)/E19,"") | G22: =IFERROR((G19-G20)/G19,"") | H22: =IFERROR((H19-H20)/H19,"") | J22: =IFERROR((J19-J20)/J19,"") | K22: =IFERROR((K19-K20)/K19,"") | M22: =IFERROR((M19-M20)/M19,"") | N22: =IFERROR((N19-N20)/N19,"") | P22: =IFERROR((P19-P20)/P19,"") | Q22: =IFERROR((Q19-Q20)/Q19,"") | S22: =IFERROR((S19-S20)/S19,"") | T22: =IFERROR((T19-T20)/T19,"") | V22: =IFERROR((V19-V20)/V19,"") | W22: =IFERROR((W19-W20)/W19,"")

Sheet Свод
A1: MainExperts · P&L · Свод по двум потокам (Платформа + Поток-1) · ₽
D2: июл.26 | G2: авг.26 | J2: сен.26 | M2: окт.26 | P2: ноя.26 | S2: дек.26 | V2: Год
A3: Код | B3: Статья / метрика | C3: Направление | D3: План | E3: Факт | F3: % | G3: План | H3: Факт | I3: % | J3: План | K3: Факт | L3: % | M3: План | N3: Факт | O3: % | P3: План | Q3: Факт | R3: % | S3: План | T3: Факт | U3: % | V3: План | W3: Факт | X3: %
B4: Выручка всего | C4: финансы | D4: =IFERROR('Платформа'!D10+'Поток-1'!D10,"") | E4: =IFERROR('Платформа'!E10+'Поток-1'!E10,"") | F4: =IFERROR(E4/E4,"") | G4: =IFERROR('Платформа'!G10+'Поток-1'!G10,"") | H4: =IFERROR('Платформа'!H10+'Поток-1'!H10,"") | I4: =IFERROR(H4/H4,"") | J4: =IFERROR('Платформа'!J10+'Поток-1'!J10,"") | K4: =IFERROR('Платформа'!K10+'Поток-1'!K10,"") | L4: =IFERROR(K4/K4,"") | M4: =IFERROR('Платформа'!M10+'Поток-1'!M10,"") | N4: =IFERROR('Платформа'!N10+'Поток-1'!N10,"") | O4: =IFERROR(N4/N4,"") | P4: =IFERROR('Платформа'!P10+'Поток-1'!P10,"") | Q4: =IFERROR('Платформа'!Q10+'Поток-1'!Q10,"") | R4: =IFERROR(Q4/Q4,"") | S4: =IFERROR('Платформа'!S10+'Поток-1'!S10,"") | T4: =IFERROR('Платформа'!T10+'Поток-1'!T10,"") | U4: =IFERROR(T4/T4,"") | V4: =IFERROR('Платформа'!V10+'Поток-1'!V10,"") | W4: =IFERROR('Платформа'!W10+'Поток-1'!W10,"") | X4: =IFERROR(W4/W4,"")
B5: Расходы всего | C5: финансы | D5: =IFERROR(SUM(D6:D12),"") | E5: =IFERROR(SUM(E6:E12),"") | F5: =IFERROR(E5/E4,"") | G5: =IFERROR(SUM(G6:G12),"") | H5: =IFERROR(SUM(H6:H12),"") | I5: =IFERROR(H5/H4,"") | J5: =IFERROR(SUM(J6:J12),"") | K5: =IFERROR(SUM(K6:K12),"") | L5: =IFERROR(K5/K4,"") | M5: =IFERROR(SUM(M6:M12),"") | N5: =IFERROR(SUM(N6:N12),"") | O5: =IFERROR(N5/N4,"") | P5: =IFERROR(SUM(P6:P12),"") | Q5: =IFERROR(SUM(Q6:Q12),"") | R5: =IFERROR(Q5/Q4,"") | S5: =IFERROR(SUM(S6:S12),"") | T5: =IFERROR(SUM(T6:T12),"") | U5: =IFERROR(T5/T4,"") | V5: =IFERROR(SUM(V6:V12),"") | W5: =IFERROR(SUM(W6:W12),"") | X5: =IFERROR(W5/W4,"")
A6: М П1 | B6: Рекламный бюджет Итого | C6: маркетинг | D6: =IFERROR('Платформа'!D12+'Поток-1'!D12,"") | E6: =IFERROR('Платформа'!E12+'Поток-1'!E12,"") | F6: =IFERROR(E6/E4,"") | G6: =IFERROR('Платформа'!G12+'Поток-1'!G12,"") | H6: =IFERROR('Платформа'!H12+'Поток-1'!H12,"") | I6: =IFERROR(H6/H4,"") | J6: =IFERROR('Платформа'!J12+'Поток-1'!J12,"") | K6: =IFERROR('Платформа'!K12+'Поток-1'!K12,"") | L6: =IFERROR(K6/K4,"") | M6: =IFERROR('Платформа'!M12+'Поток-1'!M12,"") | N6: =IFERROR('Платформа'!N12+'Поток-1'!N12,"") | O6: =IFERROR(N6/N4,"") | P6: =IFERROR('Платформа'!P12+'Поток-1'!P12,"") | Q6: =IFERROR('Платформа'!Q12+'Поток-1'!Q12,"") | R6: =IFERROR(Q6/Q4,"") | S6: =IFERROR('Платформа'!S12+'Поток-1'!S12,"") | T6: =IFERROR('Платформа'!T12+'Поток-1'!T12,"") | U6: =IFERROR(T6/T4,"") | V6: =IFERROR('Платформа'!V12+'Поток-1'!V12,"") | W6: =IFERROR('Платформа'!W12+'Поток-1'!W12,"") | X6: =IFERROR(W6/W4,"")
A7: П | B7: ФОТ Платформа | C7: операционка | D7: =IFERROR('Платформа'!D13,"") | E7: =IFERROR('Платформа'!E13,"") | F7: =IFERROR(E7/E4,"") | G7: =IFERROR('Платформа'!G13,"") | H7: =IFERROR('Платформа'!H13,"") | I7: =IFERROR(H7/H4,"") | J7: =IFERROR('Платформа'!J13,"") | K7: =IFERROR('Платформа'!K13,"") | L7: =IFERROR(K7/K4,"") | M7: =IFERROR('Платформа'!M13,"") | N7: =IFERROR('Платформа'!N13,"") | O7: =IFERROR(N7/N4,"") | P7: =IFERROR('Платформа'!P13,"") | Q7: =IFERROR('Платформа'!Q13,"") | R7: =IFERROR(Q7/Q4,"") | S7: =IFERROR('Платформа'!S13,"") | T7: =IFERROR('Платформа'!T13,"") | U7: =IFERROR(T7/T4,"") | V7: =IFERROR('Платформа'!V13,"") | W7: =IFERROR('Платформа'!W13,"") | X7: =IFERROR(W7/W4,"")
A8: П1 | B8: ФОТ Продажи (2 менеджера) | C8: продажи | D8: =IFERROR('Поток-1'!D13+'Поток-1'!D14,"") | E8: =IFERROR('Поток-1'!E13+'Поток-1'!E14,"") | F8: =IFERROR(E8/E4,"") | G8: =IFERROR('Поток-1'!G13+'Поток-1'!G14,"") | H8: =IFERROR('Поток-1'!H13+'Поток-1'!H14,"") | I8: =IFERROR(H8/H4,"") | J8: =IFERROR('Поток-1'!J13+'Поток-1'!J14,"") | K8: =IFERROR('Поток-1'!K13+'Поток-1'!K14,"") | L8: =IFERROR(K8/K4,"") | M8: =IFERROR('Поток-1'!M13+'Поток-1'!M14,"") | N8: =IFERROR('Поток-1'!N13+'Поток-1'!N14,"") | O8: =IFERROR(N8/N4,"") | P8: =IFERROR('Поток-1'!P13+'Поток-1'!P14,"") | Q8: =IFERROR('Поток-1'!Q13+'Поток-1'!Q14,"") | R8: =IFERROR(Q8/Q4,"") | S8: =IFERROR('Поток-1'!S13+'Поток-1'!S14,"") | T8: =IFERROR('Поток-1'!T13+'Поток-1'!T14,"") | U8: =IFERROR(T8/T4,"") | V8: =IFERROR('Поток-1'!V13+'Поток-1'!V14,"") | W8: =IFERROR('Поток-1'!W13+'Поток-1'!W14,"") | X8: =IFERROR(W8/W4,"")
A9: М П1 | B9: Инструменты и Сервисы | C9: операционка | D9: =IFERROR('Платформа'!D14+'Поток-1'!D15,"") | E9: =IFERROR('Платформа'!E14+'Поток-1'!E15,"") | F9: =IFERROR(E9/E4,"") | G9: =IFERROR('Платформа'!G14+'Поток-1'!G15,"") | H9: =IFERROR('Платформа'!H14+'Поток-1'!H15,"") | I9: =IFERROR(H9/H4,"") | J9: =IFERROR('Платформа'!J14+'Поток-1'!J15,"") | K9: =IFERROR('Платформа'!K14+'Поток-1'!K15,"") | L9: =IFERROR(K9/K4,"") | M9: =IFERROR('Платформа'!M14+'Поток-1'!M15,"") | N9: =IFERROR('Платформа'!N14+'Поток-1'!N15,"") | O9: =IFERROR(N9/N4,"") | P9: =IFERROR('Платформа'!P14+'Поток-1'!P15,"") | Q9: =IFERROR('Платформа'!Q14+'Поток-1'!Q15,"") | R9: =IFERROR(Q9/Q4,"") | S9: =IFERROR('Платформа'!S14+'Поток-1'!S15,"") | T9: =IFERROR('Платформа'!T14+'Поток-1'!T15,"") | U9: =IFERROR(T9/T4,"") | V9: =IFERROR('Платформа'!V14+'Поток-1'!V15,"") | W9: =IFERROR('Платформа'!W14+'Поток-1'!W15,"") | X9: =IFERROR(W9/W4,"")
A10: П | B10: AI-стоимость / Себестоимость | C10: разработка | D10: =IFERROR('Платформа'!D15+'Платформа'!D16,"") | E10: =IFERROR('Платформа'!E15+'Платформа'!E16,"") | F10: =IFERROR(E10/E4,"") | G10: =IFERROR('Платформа'!G15+'Платформа'!G16,"") | H10: =IFERROR('Платформа'!H15+'Платформа'!H16,"") | I10: =IFERROR(H10/H4,"") | J10: =IFERROR('Платформа'!J15+'Платформа'!J16,"") | K10: =IFERROR('Платформа'!K15+'Платформа'!K16,"") | L10: =IFERROR(K10/K4,"") | M10: =IFERROR('Платформа'!M15+'Платформа'!M16,"") | N10: =IFERROR('Платформа'!N15+'Платформа'!N16,"") | O10: =IFERROR(N10/N4,"") | P10: =IFERROR('Платформа'!P15+'Платформа'!P16,"") | Q10: =IFERROR('Платформа'!Q15+'Платформа'!Q16,"") | R10: =IFERROR(Q10/Q4,"") | S10: =IFERROR('Платформа'!S15+'Платформа'!S16,"") | T10: =IFERROR('Платформа'!T15+'Платформа'!T16,"") | U10: =IFERROR(T10/T4,"") | V10: =IFERROR('Платформа'!V15+'Платформа'!V16,"") | W10: =IFERROR('Платформа'!W15+'Платформа'!W16,"") | X10: =IFERROR(W10/W4,"")
A11: А | B11: Эквайринг | C11: финансы | D11: =IFERROR('Платформа'!D17+'Поток-1'!D16,"") | E11: =IFERROR('Платформа'!E17+'Поток-1'!E16,"") | F11: =IFERROR(E11/E4,"") | G11: =IFERROR('Платформа'!G17+'Поток-1'!G16,"") | H11: =IFERROR('Платформа'!H17+'Поток-1'!H16,"") | I11: =IFERROR(H11/H4,"") | J11: =IFERROR('Платформа'!J17+'Поток-1'!J16,"") | K11: =IFERROR('Платформа'!K17+'Поток-1'!K16,"") | L11: =IFERROR(K11/K4,"") | M11: =IFERROR('Платформа'!M17+'Поток-1'!M16,"") | N11: =IFERROR('Платформа'!N17+'Поток-1'!N16,"") | O11: =IFERROR(N11/N4,"") | P11: =IFERROR('Платформа'!P17+'Поток-1'!P16,"") | Q11: =IFERROR('Платформа'!Q17+'Поток-1'!Q16,"") | R11: =IFERROR(Q11/Q4,"") | S11: =IFERROR('Платформа'!S17+'Поток-1'!S16,"") | T11: =IFERROR('Платформа'!T17+'Поток-1'!T16,"") | U11: =IFERROR(T11/T4,"") | V11: =IFERROR('Платформа'!V17+'Поток-1'!V16,"") | W11: =IFERROR('Платформа'!W17+'Поток-1'!W16,"") | X11: =IFERROR(W11/W4,"")
A12: А | B12: Административные | C12: финансы | D12: =IFERROR('Платформа'!D18+'Поток-1'!D17,"") | E12: =IFERROR('Платформа'!E18+'Поток-1'!E17,"") | F12: =IFERROR(E12/E4,"") | G12: =IFERROR('Платформа'!G18+'Поток-1'!G17,"") | H12: =IFERROR('Платформа'!H18+'Поток-1'!H17,"") | I12: =IFERROR(H12/H4,"") | J12: =IFERROR('Платформа'!J18+'Поток-1'!J17,"") | K12: =IFERROR('Платформа'!K18+'Поток-1'!K17,"") | L12: =IFERROR(K12/K4,"") | M12: =IFERROR('Платформа'!M18+'Поток-1'!M17,"") | N12: =IFERROR('Платформа'!N18+'Поток-1'!N17,"") | O12: =IFERROR(N12/N4,"") | P12: =IFERROR('Платформа'!P18+'Поток-1'!P17,"") | Q12: =IFERROR('Платформа'!Q18+'Поток-1'!Q17,"") | R12: =IFERROR(Q12/Q4,"") | S12: =IFERROR('Платформа'!S18+'Поток-1'!S17,"") | T12: =IFERROR('Платформа'!T18+'Поток-1'!T17,"") | U12: =IFERROR(T12/T4,"") | V12: =IFERROR('Платформа'!V18+'Поток-1'!V17,"") | W12: =IFERROR('Платформа'!W18+'Поток-1'!W17,"") | X12: =IFERROR(W12/W4,"")
B13: Маржинальная прибыль | C13: финансы | D13: =IFERROR(D4-D5,"") | E13: =IFERROR(E4-E5,"") | F13: =IFERROR(E13/E4,"") | G13: =IFERROR(G4-G5,"") | H13: =IFERROR(H4-H5,"") | I13: =IFERROR(H13/H4,"") | J13: =IFERROR(J4-J5,"") | K13: =IFERROR(K4-K5,"") | L13: =IFERROR(K13/K4,"") | M13: =IFERROR(M4-M5,"") | N13: =IFERROR(N4-N5,"") | O13: =IFERROR(N13/N4,"") | P13: =IFERROR(P4-P5,"") | Q13: =IFERROR(Q4-Q5,"") | R13: =IFERROR(Q13/Q4,"") | S13: =IFERROR(S4-S5,"") | T13: =IFERROR(T4-T5,"") | U13: =IFERROR(T13/T4,"") | V13: =IFERROR(V4-V5,"") | W13: =IFERROR(W4-W5,"") | X13: =IFERROR(W13/W4,"")

Sheet Справка
A1: D3-SPC-01 · P&L MainExperts по потокам — структура присланного файла, наши продукты
A3: Цвета (как в оригинале): зелёный — Выручка всего / Маржинальная прибыль; красный — Расходы;
A4: серый — считается автоматически (не заполнять); белое — ввод основателя; жёлтый/синий — метка воронки.
A6: Структура повторяет присланный P&L (розница). Каналы заменены: «Сайт» → «Платформа» (Поток-2);
A7: личные продажи → «Поток-1» (агентство, 2 менеджера: лиды→созвоны→оплаты→суммы); «Свод» по двум потокам.
A8: ФОТ Платформы — единая строка на всю команду платформы (разработка, маркетинг, владелец, Саша, Вадим).
A10: Честно: объёмы/суммы — ввод основателя; эквайринг 10% (Робокасса, docs/06); пороги/цели не заданы.
A11: Формулы (конверсии, CAC, маржа, свод) считаются автоматически (IFERROR). План/Факт помесячно + Год.
A12: Оговорка: чистую юнит-экономику потоков обычно не смешивают; «Свод» консолидирует по запросу основателя.
A13: Источники: docs/dms/documents/D3-SPC-01__pnl-model.md · docs/06 · docs/01.
