Workbook

Sheet Инструкция
A1: Реестр контактов партнёрской сети MainExperts
A2: Назначение: управление обзвоном первой волны (10 разговоров за 5 дней, созвон 09.09.2026) и передача подключённых партнёров в кабинет. Соответствует материалу К12 из технического задания docs/15-partner-network-tz.md.
A4: Как заполнять
A5: 1. Синий текст — поля для ввода. Чёрный — формулы, не трогать. Выпадающие списки берутся с листа «Справочники»; новые значения добавляйте там.
A6: 2. Одна строка — один человек или организация. «Контакт состоялся» ставится только после двустороннего обмена: отправка без ответа контактом не считается.
A7: 3. «Главный вопрос партнёра» и «Возражение» — обязательны после первого разговора: по ним правятся условия и ответы на возражения (К09).
A8: 4. «Отправленные материалы» — коды К01…К09 через запятую. «Следующее действие» и его дата — всегда заполнены, иначе строка мертва; просроченные подсвечиваются в колонке «Просрочено».
A9: 5. «Резидент РФ» — обязательно до отправки условий: нерезидентам в пилоте выплаты не производятся (ТЗ, ПРАВ-11). «Круг основателя» — да/нет: такие покупки в выводы о спросе не идут.
A10: 6. После принятия оферты в кабинете вписать partner_id и перевести стадию в «Подключён».
A12: Что уже внесено
A13: Восемь строк — контакты, прозвучавшие на созвонах 08.09 и 09.09: имена только те, что были названы, остальное оставлено пустым и помечено «уточнить» в заметках. Строки-заготовки для контактов основателя заменить реальными людьми.
A15: Персональные данные
... A19: Имя: Марина П. · Контакт: @username · Кто познакомил: Основатель (Макс) · Когорта: Активные преподаватели · Аудитория: 12 учеников 14–17 лет, английский · Страна семей: Россия · Резидент: Да · Продукт пройден: Нет · Стадия: Условия отправлены · Дата первого контакта: 12.09.2026 · Главный вопрос: «почему 20 000, если в интернете 12 000» · Реакция: Дорого для его семей · Возражение: Дорого · Материалы: К01, К02, К03 · Следующее действие: показать образец отчёта и расчёт на трёх ценах · Дата: 15.09.2026 · Ответственный: Маркетинг (Игорь) · Круг основателя: Да.

Sheet Контакты
A1: № | B1: Имя | C1: Контакт (мессенджер, телефон, почта) | D1: Кто познакомил | E1: Когорта | F1: Аудитория и возраст детей | G1: Страна семей | H1: Резидент РФ | I1: Продукт пройден | J1: Стадия | K1: Дата первого контакта | L1: Главный вопрос партнёра | M1: Реакция на цену | N1: Возражение | O1: Отправленные материалы | P1: Следующее действие | Q1: Дата следующего действия | R1: Ответственный | S1: partner_id (после подключения) | T1: Круг основателя | U1: Просрочено | V1: Заметки и источник
A2: 1 | B2: Радион | D2: Команда (общался Макс) | E2: Нишевые блогеры и предприниматели с детьми | F2: Семейная аудитория в Instagram (уточнить размер и возраст детей) | G2: Россия (уточнить) | H2: Не знаем | I2: Да, бесплатная выдача | J2: Есть интерес | L2: Готов выложить; ждёт запуска | M2: Не обсуждали | N2: Нет | P2: Согласовать формат публикации (К07), создать код с ценой, взять данные для реестра | R2: Основатель (Макс) | T2: Да | U2: =IF(AND(Q2<>"",Q2<TODAY(),ISERROR(MATCH(J2,{"Продающий (первая оплата)","Отказ","Отложен"},0))),"Да","") | V2: Созвон 09.09: «он уже давно ждёт, готов, есть Instagram, тесты сделали». Первый кандидат на публикацию. Маркировка рекламы и площадка — к юристу до публикации (ПРАВ-09).
A3: 2 | B3: Денис | D3: Основатель (Макс) | E3: Знакомые основателя | H3: Не знаем | I3: Не знаем | J3: Потенциальный | M3: Не обсуждали | N3: Стыдно брать деньги со знакомых | P3: Личный разговор; предложить рекомендацию по МРЦ без вознаграждения или с отложенными баллами | R3: Основатель (Макс) | T3: Да | U3: =IF(AND(Q3<>"",Q3<TODAY(),ISERROR(MATCH(J3,{"Продающий (первая оплата)","Отказ","Отложен"},0))),"Да","") | V3: Созвон 08.09: пример человека, который не хочет зарабатывать на друзьях (идея бонусного счёта). Созвон 09.09: «Денис есть тоже». Роль и контакт уточнить.
A4: 3 | B4: Преподаватель биологии с каналом (имя не названо) | D4: Основатель (Макс) | E4: Активные преподаватели | F4: Подростки; ведёт свой канал по биологии | H4: Не знаем | I4: Нет | J4: Потенциальный | M4: Не обсуждали | N4: Нет | P4: Взять контакт у основателя; личный разговор | R4: Основатель (Макс) | T4: Да | U4: =IF(AND(Q4<>"",Q4<TODAY(),ISERROR(MATCH(J4,{"Продающий (первая оплата)","Отказ","Отложен"},0))),"Да","") | V4: Созвон 09.09: «человек, который ведёт свой по биологии… заработал» — активный учитель с аудиторией. Имя и данные уточнить.
A5: 4 | B5: Контакт основателя 1 (преподаватель) | D5: Основатель (Макс) | E5: Знакомые основателя | H5: Не знаем | I5: Не знаем | J5: Потенциальный | M5: Не обсуждали | N5: Нет | P5: Получить контакт у основателя (обещано 2–3) | R5: Основатель (Макс) | T5: Да | U5: =IF(AND(Q5<>"",Q5<TODAY(),ISERROR(MATCH(J5,{"Продающий (первая оплата)","Отказ","Отложен"},0))),"Да","") | V5: Созвон 09.09: «я тебе дам свои какие-то контакты… 2–3». Строка-заготовка.
A6: 5 | B6: Контакт основателя 2 (преподаватель) | D6: Основатель (Макс) | E6: Знакомые основателя | H6: Не знаем | I6: Не знаем | J6: Потенциальный | M6: Не обсуждали | N6: Нет | P6: Получить контакт у основателя | R6: Основатель (Макс) | T6: Да | U6: =IF(AND(Q6<>"",Q6<TODAY(),ISERROR(MATCH(J6,{"Продающий (первая оплата)","Отказ","Отложен"},0))),"Да","") | V6: Строка-заготовка.
A7: 6 | B7: Преподаватели в Грузии (Вадим) | D7: Продукт (Вадим) | E7: Активные преподаватели | G7: Грузия | H7: Нет | I7: Не знаем | J7: Потенциальный | M7: Не обсуждали | N7: Нет | P7: Вадим смотрит кандидатов. Внимание: нерезиденты в пилоте не выплачиваются (ПРАВ-11); только после заключения юриста | R7: Продукт (Вадим) | T7: Нет | U7: =IF(AND(Q7<>"",Q7<TODAY(),ISERROR(MATCH(J7,{"Продающий (первая оплата)","Отказ","Отложен"},0))),"Да","") | V7: Созвон 09.09: «Вадим, посмотри, может кто-то в Грузии есть учителей». Для пилота непригодны до решения по нерезидентам.
A8: 7 | B8: Психологи из таблицы «профи» | D8: Команда | E8: Психологи (осторожно, другое предложение) | G8: Россия | H8: Не знаем | I8: Не знаем | J8: Отложен | M8: Не обсуждали | N8: Нет | P8: Не приглашать в первую волну; отдельное предложение позже | R8: Маркетинг (Игорь) | T8: Нет | U8: =IF(AND(Q8<>"",Q8<TODAY(),ISERROR(MATCH(J8,{"Продающий (первая оплата)","Отказ","Отложен"},0))),"Да","") | V8: Созвон 09.09: «таблица в профи, там чуть-чуть психологи… с ними поаккуратнее». Таблица в репозитории отсутствует.
A9: 8 | B9: Таня (довольная клиентка, пример) | D9: Основатель (Макс) | E9: Довольные родители | F9: Родитель | H9: Не знаем | I9: Да, купил | J9: Потенциальный | M9: Не обсуждали | N9: Нет | P9: Уточнить у основателя, реальный ли контакт; предложить поделиться опытом | R9: Основатель (Макс) | T9: Да | U9: =IF(AND(Q9<>"",Q9<TODAY(),ISERROR(MATCH(J9,{"Продающий (первая оплата)","Отказ","Отложен"},0))),"Да","") | V9: Созвон 09.09: пример рекомендации «как я, Таня, там классные ребята». Реальность контакта не подтверждена.
A10: =IF(B10="","",ROW()-1) | U10: =IF(AND(Q10<>"",Q10<TODAY(),ISERROR(MATCH(J10,{"Продающий (первая оплата)","Отказ","Отложен"},0))),"Да","")
A11: =IF(B11="","",ROW()-1) | U11: =IF(AND(Q11<>"",Q11<TODAY(),ISERROR(MATCH(J11,{"Продающий (первая оплата)","Отказ","Отложен"},0))),"Да","")
A12: =IF(B12="","",ROW()-1) | U12: =IF(AND(Q12<>"",Q12<TODAY(),ISERROR(MATCH(J12,{"Продающий (первая оплата)","Отказ","Отложен"},0))),"Да","")
A13: =IF(B13="","",ROW()-1) | U13: =IF(AND(Q13<>"",Q13<TODAY(),ISERROR(MATCH(J13,{"Продающий (первая оплата)","Отказ","Отложен"},0))),"Да","")
A14: =IF(B14="","",ROW()-1) | U14: =IF(AND(Q14<>"",Q14<TODAY(),ISERROR(MATCH(J14,{"Продающий (первая оплата)","Отказ","Отложен"},0))),"Да","")
A15: =IF(B15="","",ROW()-1) | U15: =IF(AND(Q15<>"",Q15<TODAY(),ISERROR(MATCH(J15,{"Продающий (первая оплата)","Отказ","Отложен"},0))),"Да","")
A16: =IF(B16="","",ROW()-1) | U16: =IF(AND(Q16<>"",Q16<TODAY(),ISERROR(MATCH(J16,{"Продающий (первая оплата)","Отказ","Отложен"},0))),"Да","")
A17: =IF(B17="","",ROW()-1) | U17: =IF(AND(Q17<>"",Q17<TODAY(),ISERROR(MATCH(J17,{"Продающий (первая оплата)","Отказ","Отложен"},0))),"Да","")
A18: =IF(B18="","",ROW()-1) | U18: =IF(AND(Q18<>"",Q18<TODAY(),ISERROR(MATCH(J18,{"Продающий (первая оплата)","Отказ","Отложен"},0))),"Да","")
A19: =IF(B19="","",ROW()-1) | U19: =IF(AND(Q19<>"",Q19<TODAY(),ISERROR(MATCH(J19,{"Продающий (первая оплата)","Отказ","Отложен"},0))),"Да","")
A20: =IF(B20="","",ROW()-1) | U20: =IF(AND(Q20<>"",Q20<TODAY(),ISERROR(MATCH(J20,{"Продающий (первая оплата)","Отказ","Отложен"},0))),"Да","")
A21: =IF(B21="","",ROW()-1) | U21: =IF(AND(Q21<>"",Q21<TODAY(),ISERROR(MATCH(J21,{"Продающий (первая оплата)","Отказ","Отложен"},0))),"Да","")
... A60: =IF(B60="","",ROW()-1) | U60: =IF(AND(Q60<>"",Q60<TODAY(),ISERROR(MATCH(J60,{"Продающий (первая оплата)","Отказ","Отложен"},0))),"Да","")

Sheet Сводка
A1: Сводка по реестру контактов партнёрской сети
A2: Все числа — формулы по листу «Контакты». Цель первой недели: не менее 10 состоявшихся разговоров за 5 дней (созвон 09.09).
A4: Показатель | B4: Значение | C4: Цель
A5: Строк в реестре | B5: =COUNTA(Контакты!$B$2:$B$60)
A6: Состоявшихся контактов (двусторонний обмен и дальше) | B6: =COUNTIF(Контакты!$J$2:$J$60,"Контакт состоялся")+COUNTIF(Контакты!$J$2:$J$60,"Есть интерес")+COUNTIF(Контакты!$J$2:$J$60,"Условия отправлены")+COUNTIF(Контакты!$J$2:$J$60,"Подключён (оферта принята)")+COUNTIF(Контакты!$J$2:$J$60,"Активирован (первое обращение)")+COUNTIF(Контакты!$J$2:$J$60,"Продающий (первая оплата)") | C6: 10
A7: Есть интерес | B7: =COUNTIF(Контакты!$J$2:$J$60,"Есть интерес")
A8: Условия отправлены | B8: =COUNTIF(Контакты!$J$2:$J$60,"Условия отправлены")
A9: Подключено (оферта принята) | B9: =COUNTIF(Контакты!$J$2:$J$60,"Подключён (оферта принята)") | C9: 2
A10: Активировано (первое обращение) | B10: =COUNTIF(Контакты!$J$2:$J$60,"Активирован (первое обращение)")
A11: Продающих (первая оплата) | B11: =COUNTIF(Контакты!$J$2:$J$60,"Продающий (первая оплата)")
A12: Отказов | B12: =COUNTIF(Контакты!$J$2:$J$60,"Отказ")
A13: Просроченных следующих действий | B13: =COUNTIF(Контакты!$U$2:$U$60,"Да") | C13: 0
A14: Из круга основателя | B14: =COUNTIF(Контакты!$T$2:$T$60,"Да")
A15: Нерезидентов (в пилоте не выплачиваются) | B15: =COUNTIF(Контакты!$H$2:$H$60,"Нет")
A17: По когортам
A18: Когорта | B18: Всего | C18: Контакт и дальше | D18: Подключено и дальше
A19: Активные преподаватели | B19: =COUNTIF(Контакты!$E$2:$E$60,A19) | C19: =COUNTIFS(Контакты!$E$2:$E$60,A19,Контакты!$J$2:$J$60,"Контакт состоялся")+COUNTIFS(Контакты!$E$2:$E$60,A19,Контакты!$J$2:$J$60,"Есть интерес")+COUNTIFS(Контакты!$E$2:$E$60,A19,Контакты!$J$2:$J$60,"Условия отправлены")+COUNTIFS(Контакты!$E$2:$E$60,A19,Контакты!$J$2:$J$60,"Подключён (оферта принята)")+COUNTIFS(Контакты!$E$2:$E$60,A19,Контакты!$J$2:$J$60,"Активирован (первое обращение)")+COUNTIFS(Контакты!$E$2:$E$60,A19,Контакты!$J$2:$J$60,"Продающий (первая оплата)") | D19: =COUNTIFS(Контакты!$E$2:$E$60,A19,Контакты!$J$2:$J$60,"Подключён (оферта принята)")+COUNTIFS(Контакты!$E$2:$E$60,A19,Контакты!$J$2:$J$60,"Активирован (первое обращение)")+COUNTIFS(Контакты!$E$2:$E$60,A19,Контакты!$J$2:$J$60,"Продающий (первая оплата)")
A20: Нишевые блогеры и предприниматели с детьми | B20: =COUNTIF(Контакты!$E$2:$E$60,A20) | C20: =COUNTIFS(Контакты!$E$2:$E$60,A20,Контакты!$J$2:$J$60,"Контакт состоялся")+COUNTIFS(Контакты!$E$2:$E$60,A20,Контакты!$J$2:$J$60,"Есть интерес")+COUNTIFS(Контакты!$E$2:$E$60,A20,Контакты!$J$2:$J$60,"Условия отправлены")+COUNTIFS(Контакты!$E$2:$E$60,A20,Контакты!$J$2:$J$60,"Подключён (оферта принята)")+COUNTIFS(Контакты!$E$2:$E$60,A20,Контакты!$J$2:$J$60,"Активирован (первое обращение)")+COUNTIFS(Контакты!$E$2:$E$60,A20,Контакты!$J$2:$J$60,"Продающий (первая оплата)") | D20: =COUNTIFS(Контакты!$E$2:$E$60,A20,Контакты!$J$2:$J$60,"Подключён (оферта принята)")+COUNTIFS(Контакты!$E$2:$E$60,A20,Контакты!$J$2:$J$60,"Активирован (первое обращение)")+COUNTIFS(Контакты!$E$2:$E$60,A20,Контакты!$J$2:$J$60,"Продающий (первая оплата)")
A21: Знакомые основателя | B21: =COUNTIF(Контакты!$E$2:$E$60,A21) | C21: =COUNTIFS(Контакты!$E$2:$E$60,A21,Контакты!$J$2:$J$60,"Контакт состоялся")+COUNTIFS(Контакты!$E$2:$E$60,A21,Контакты!$J$2:$J$60,"Есть интерес")+COUNTIFS(Контакты!$E$2:$E$60,A21,Контакты!$J$2:$J$60,"Условия отправлены")+COUNTIFS(Контакты!$E$2:$E$60,A21,Контакты!$J$2:$J$60,"Подключён (оферта принята)")+COUNTIFS(Контакты!$E$2:$E$60,A21,Контакты!$J$2:$J$60,"Активирован (первое обращение)")+COUNTIFS(Контакты!$E$2:$E$60,A21,Контакты!$J$2:$J$60,"Продающий (первая оплата)") | D21: =COUNTIFS(Контакты!$E$2:$E$60,A21,Контакты!$J$2:$J$60,"Подключён (оферта принята)")+COUNTIFS(Контакты!$E$2:$E$60,A21,Контакты!$J$2:$J$60,"Активирован (первое обращение)")+COUNTIFS(Контакты!$E$2:$E$60,A21,Контакты!$J$2:$J$60,"Продающий (первая оплата)")
A22: Довольные родители | B22: =COUNTIF(Контакты!$E$2:$E$60,A22) | C22: =COUNTIFS(Контакты!$E$2:$E$60,A22,Контакты!$J$2:$J$60,"Контакт состоялся")+COUNTIFS(Контакты!$E$2:$E$60,A22,Контакты!$J$2:$J$60,"Есть интерес")+COUNTIFS(Контакты!$E$2:$E$60,A22,Контакты!$J$2:$J$60,"Условия отправлены")+COUNTIFS(Контакты!$E$2:$E$60,A22,Контакты!$J$2:$J$60,"Подключён (оферта принята)")+COUNTIFS(Контакты!$E$2:$E$60,A22,Контакты!$J$2:$J$60,"Активирован (первое обращение)")+COUNTIFS(Контакты!$E$2:$E$60,A22,Контакты!$J$2:$J$60,"Продающий (первая оплата)") | D22: =COUNTIFS(Контакты!$E$2:$E$60,A22,Контакты!$J$2:$J$60,"Подключён (оферта принята)")+COUNTIFS(Контакты!$E$2:$E$60,A22,Контакты!$J$2:$J$60,"Активирован (первое обращение)")+COUNTIFS(Контакты!$E$2:$E$60,A22,Контакты!$J$2:$J$60,"Продающий (первая оплата)")
A23: Психологи (осторожно, другое предложение) | B23: =COUNTIF(Контакты!$E$2:$E$60,A23) | C23: =COUNTIFS(Контакты!$E$2:$E$60,A23,Контакты!$J$2:$J$60,"Контакт состоялся")+COUNTIFS(Контакты!$E$2:$E$60,A23,Контакты!$J$2:$J$60,"Есть интерес")+COUNTIFS(Контакты!$E$2:$E$60,A23,Контакты!$J$2:$J$60,"Условия отправлены")+COUNTIFS(Контакты!$E$2:$E$60,A23,Контакты!$J$2:$J$60,"Подключён (оферта принята)")+COUNTIFS(Контакты!$E$2:$E$60,A23,Контакты!$J$2:$J$60,"Активирован (первое обращение)")+COUNTIFS(Контакты!$E$2:$E$60,A23,Контакты!$J$2:$J$60,"Продающий (первая оплата)") | D23: =COUNTIFS(Контакты!$E$2:$E$60,A23,Контакты!$J$2:$J$60,"Подключён (оферта принята)")+COUNTIFS(Контакты!$E$2:$E$60,A23,Контакты!$J$2:$J$60,"Активирован (первое обращение)")+COUNTIFS(Контакты!$E$2:$E$60,A23,Контакты!$J$2:$J$60,"Продающий (первая оплата)")
A24: Учебные центры и сообщества (после пилота) | B24: =COUNTIF(Контакты!$E$2:$E$60,A24) | C24: =COUNTIFS(Контакты!$E$2:$E$60,A24,Контакты!$J$2:$J$60,"Контакт состоялся")+COUNTIFS(Контакты!$E$2:$E$60,A24,Контакты!$J$2:$J$60,"Есть интерес")+COUNTIFS(Контакты!$E$2:$E$60,A24,Контакты!$J$2:$J$60,"Условия отправлены")+COUNTIFS(Контакты!$E$2:$E$60,A24,Контакты!$J$2:$J$60,"Подключён (оферта принята)")+COUNTIFS(Контакты!$E$2:$E$60,A24,Контакты!$J$2:$J$60,"Активирован (первое обращение)")+COUNTIFS(Контакты!$E$2:$E$60,A24,Контакты!$J$2:$J$60,"Продающий (первая оплата)") | D24: =COUNTIFS(Контакты!$E$2:$E$60,A24,Контакты!$J$2:$J$60,"Подключён (оферта принята)")+COUNTIFS(Контакты!$E$2:$E$60,A24,Контакты!$J$2:$J$60,"Активирован (первое обращение)")+COUNTIFS(Контакты!$E$2:$E$60,A24,Контакты!$J$2:$J$60,"Продающий (первая оплата)")
A25: Эксперты платформы | B25: =COUNTIF(Контакты!$E$2:$E$60,A25) | C25: =COUNTIFS(Контакты!$E$2:$E$60,A25,Контакты!$J$2:$J$60,"Контакт состоялся")+COUNTIFS(Контакты!$E$2:$E$60,A25,Контакты!$J$2:$J$60,"Есть интерес")+COUNTIFS(Контакты!$E$2:$E$60,A25,Контакты!$J$2:$J$60,"Условия отправлены")+COUNTIFS(Контакты!$E$2:$E$60,A25,Контакты!$J$2:$J$60,"Подключён (оферта принята)")+COUNTIFS(Контакты!$E$2:$E$60,A25,Контакты!$J$2:$J$60,"Активирован (первое обращение)")+COUNTIFS(Контакты!$E$2:$E$60,A25,Контакты!$J$2:$J$60,"Продающий (первая оплата)") | D25: =COUNTIFS(Контакты!$E$2:$E$60,A25,Контакты!$J$2:$J$60,"Подключён (оферта принята)")+COUNTIFS(Контакты!$E$2:$E$60,A25,Контакты!$J$2:$J$60,"Активирован (первое обращение)")+COUNTIFS(Контакты!$E$2:$E$60,A25,Контакты!$J$2:$J$60,"Продающий (первая оплата)")

Sheet Справочники
A1: Справочники для выпадающих списков листа «Контакты». Менять только здесь.
A3: Когорта | B3: Стадия | C3: Реакция на цену | D3: Возражение | E3: Да/нет | F3: Продукт пройден | G3: Материалы | H3: Ответственный
A4: Активные преподаватели | B4: Потенциальный | C4: Не обсуждали | D4: Нет | E4: Да | F4: Нет | G4: К01 страница о продукте | H4: Маркетинг (Игорь)
A5: Нишевые блогеры и предприниматели с детьми | B5: Контакт состоялся | C5: Дорого для его семей | D5: Дорого | E5: Нет | F5: Да, купил | G5: К02 образец результата | H5: Основатель (Макс)
A6: Знакомые основателя | B6: Есть интерес | C6: Нормально | D6: Дешевле у другого | E6: Не знаем | F6: Да, бесплатная выдача | G6: К03 условия | H6: Продажи (Александр)
A7: Довольные родители | B7: Условия отправлены | C7: Хочет продавать дороже | D7: Надо ещё платить | F7: Не знаем | G7: К04 экономика примерами | H7: Продукт (Вадим)
A8: Психологи (осторожно, другое предложение) | B8: Подключён (оферта принята) | C8: Мало для партнёра (5 000) | D8: Стыдно брать деньги со знакомых | G8: К05 быстрый старт | H8: Платежи (Даниил)
A9: Учебные центры и сообщества (после пилота) | B9: Активирован (первое обращение) | D9: Продешевлю аудиторию | G9: К06 сообщения семье
A10: Эксперты платформы | B10: Продающий (первая оплата) | D10: Не понимаю продукт | G10: К07 сценарии публикации
B11: Отказ | D11: Нет времени | G11: К08 страница семьи
B12: Отложен | D12: Другое | G12: К09 ответы на возражения
