Workbook

Sheet Паспорт
A1: ПАСПОРТ ЗАПУСКА РЕКЛАМНОЙ КАМПАНИИ — MainExperts · Поток 2 · квиз-посадочная
A2: НЕВАЛИДИРОВАННАЯ ГИПОТЕЗА: «скрининг оцифровывает страхи родителя → родитель покупает диагностику». Кампания и есть её проверка — так трактовать результаты.
A4: Название кампании | C4: например: KVZ-2026-01
A5: Цель | B5: Проверка гипотезы скрининга платным трафиком до целевых ДРР/CPL
A6: Ячейка 1 (канал × рынок) | B6: VK → квиз · рынок СНГ
A7: Ячейка 2 (канал × рынок) | B7: Meta → квиз · рынок MENA
A8: Оффер | B8: Продаём профориентацию; скрининг — бесплатная проба
A9: Шаг после квиза (развилка флоу) | B9: [заполнить] | C9: кандидат: оплата после скрининга (флоу 18.06); решение, не данность
A10: Дата решения по флоу | C10: обязательное поле
A11: Кто принял решение (роль) | C11: владелец кампании
A12: Бюджет ячейки 1, $ | C12: минимум 400 $ — внутренний норматив
A13: Бюджет ячейки 2, $ | C13: минимум 400 $ — внутренний норматив
A14: Период | B14: [заполнить]
A15: KPI: ДРР-цель, % | C15: ключевой KPI (канон)
A16: KPI: CPL-потолок, $ | C16: прокси
A17: KPI: конверсия квиза, % | C17: завершение ÷ старт
A18: Статус | B18: черновик | C18: черновик / к запуску / тест / масштабирование / завершена
A19: Аудитория закупки | B19: родители 38–50 (персонажи кастдева) | C19: развилка «родитель или подросток» не закрыта — закупка на родителя
A20: Направления (роли, без имён) | B20: таргет · посадочная · аналитика · платежи · методология · юридическое · владелец кампании
A22: Принадлежность: Поток 2 (платформа). Из трёх целей раннего привлечения — проверка гипотезы скрининга. Метрики потоков не объединяются. Названия методик в клиентских текстах запрещены (только рабочие переименования).

Sheet План работ
A1: # | B1: Этап | C1: Задача | D1: Артефакт на выходе | E1: Направление | F1: Начало | G1: Срок | H1: Зависит от # | I1: Статус
A2: 1 | B2: 0 · Доступы и кабинеты | C2: Рекламные кабинеты VK и Meta: создать/проверить, биллинг | D2: доступы к кабинетам | E2: таргет | I2: Очередь
A3: 2 | B3: 0 · Доступы и кабинеты | C3: Доступы: Метрика, GA, Data Studio | D3: доступы аналитики | E3: аналитика | I3: Очередь
A4: 3 | B4: 1 · Посадочная-квиз | C4: Логика вопросов квиза (~18 вопросов, 6 шкал; e-mail до результата — флоу 18.06) | D4: сценарий квиза | E4: методология | I4: Очередь
A5: 4 | B5: 1 · Посадочная-квиз | C5: Экраны: истории + карусель, 5 слоганов-вариаций | D5: макеты экранов | E5: посадочная | H5: 3 | I5: Очередь
A6: 5 | B6: 1 · Посадочная-квиз | C6: Мобильная версия и скорость загрузки | D6: посадочная прошла проверку с телефона | E6: посадочная | H6: 4 | I6: Очередь
A7: 6 | B7: 2 · Аналитика | C7: Пиксели VK/Meta и события по цепочке | D7: события летят | E7: аналитика | H7: 1 | I7: Очередь
A8: 7 | B8: 2 · Аналитика | C8: Карта UTM и шаблон ссылки | D8: карта UTM | E8: аналитика | I8: Очередь
A9: 8 | B9: 2 · Аналитика | C9: Сквозная связка до оплаты (ручное сведение с источником) | D9: регламент сведения | E9: аналитика | H9: 6 | I9: Очередь
A10: 9 | B10: 3 · Платёж и правовое | C10: Тестовая транзакция Robokassa (комиссия 10% — канон) | D10: чек тестовой оплаты | E10: платежи | I10: Очередь
A11: 10 | B11: 3 · Платёж и правовое | C11: Оферта и согласия на посадочной | D11: тексты размещены | E11: юридическое | I11: Очередь
A12: 11 | B12: 3 · Платёж и правовое | C12: Возрастная логика и согласие родителя (несовершеннолетние) | D12: механика согласия | E12: юридическое | H12: 10 | I12: Очередь
A13: 12 | B13: 4 · Креативы и аудитории | C13: Пять слоганов под A/B (заглушка: «Определи будущее твоего ребёнка») | D13: список слоганов | E13: посадочная | I13: Очередь
A14: 13 | B14: 4 · Креативы и аудитории | C14: Аудитории и исключения: родители 38–50, СНГ (VK) / MENA (Meta) | D14: карта аудиторий | E14: таргет | I14: Очередь
A15: 14 | B15: 5 · Настройка и маркировка | C15: Сборка кампаний в кабинетах (ячейки VK×СНГ, Meta×MENA) | D15: кампании в черновиках | E15: таргет | H15: 13 | I15: Очередь
A16: 15 | B16: 5 · Настройка и маркировка | C16: Маркировка РФ: ОРД, erid | D16: erid получены | E16: юридическое | H16: 14 | I16: Очередь
A17: 16 | B17: 6 · Тестовый запуск | C17: Лимиты и стоп-правила теста согласованы | D17: стоп-правила в брифе | E17: владелец кампании | I17: Очередь
A18: 17 | B18: 6 · Тестовый запуск | C18: Тестовый запуск ячеек | D18: кампании активны | E18: таргет | H18: 16 | I18: Очередь
A19: 18 | B19: 7 · Разбор теста и решение | C19: Разбор теста по порогам измерений | D19: отчёт разбора | E19: аналитика | H19: 17 | I19: Очередь
A20: 19 | B20: 7 · Разбор теста и решение | C20: Решение: стоп / правка / масштабирование | D20: зафиксированное решение с датой | E20: владелец кампании | H20: 18 | I20: Очередь
A21: 20 | B21: 8 · Масштабирование | C21: Перенос бюджета на связки-победители | D21: обновлённые кампании | E21: таргет | H21: 19 | I21: Очередь
A22: 21 | B22: 9 · Отчётность и ретроспектива | C22: Финальный отчёт: ДРР, CPL, конверсии по шагам | D22: отчёт кампании | E22: аналитика | H22: 20 | I22: Очередь
A23: 22 | B23: 9 · Отчётность и ретроспектива | C23: Ретроспектива и уроки | D23: заметка в базу знаний | E23: владелец кампании | H23: 21 | I23: Очередь

Sheet Спринт-доска
A1: Спринт-доска = столбец «Статус» на листе «План работ»
A2: Сводка считается автоматически:
A4: Очередь | B4: =COUNTIF('План работ'!I:I,"Очередь")
A5: В работе | B5: =COUNTIF('План работ'!I:I,"В работе")
A6: Проверка | B6: =COUNTIF('План работ'!I:I,"Проверка")
A7: Готово | B7: =COUNTIF('План работ'!I:I,"Готово")
A9: Всего задач | B9: =COUNTA('План работ'!C2:C60)

Sheet Гант
A1: Старт диаграммы (дата): | B1: =TODAY()
A2: Полосы появляются, когда в «Плане работ» заданы Начало и Срок. Сетка — 42 дня от старта.
A4: Задача (из плана) | B4: =$B$1+0 | C4: =$B$1+1 | D4: =$B$1+2 | E4: =$B$1+3 | F4: =$B$1+4 | G4: =$B$1+5 | H4: =$B$1+6 | I4: =$B$1+7 | J4: =$B$1+8 | K4: =$B$1+9 | L4: =$B$1+10 | M4: =$B$1+11 | N4: =$B$1+12 | O4: =$B$1+13 | P4: =$B$1+14 | Q4: =$B$1+15 | R4: =$B$1+16 | S4: =$B$1+17 | T4: =$B$1+18 | U4: =$B$1+19 | V4: =$B$1+20 | W4: =$B$1+21 | X4: =$B$1+22 | Y4: =$B$1+23 | Z4: =$B$1+24 | AA4: =$B$1+25 | AB4: =$B$1+26 | AC4: =$B$1+27 | AD4: =$B$1+28 | AE4: =$B$1+29 | AF4: =$B$1+30 | AG4: =$B$1+31 | AH4: =$B$1+32 | AI4: =$B$1+33 | AJ4: =$B$1+34 | AK4: =$B$1+35 | AL4: =$B$1+36 | AM4: =$B$1+37 | AN4: =$B$1+38 | AO4: =$B$1+39 | AP4: =$B$1+40 | AQ4: =$B$1+41
A5: ='План работ'!C2
A6: ='План работ'!C3
A7: ='План работ'!C4
A8: ='План работ'!C5
A9: ='План работ'!C6
A10: ='План работ'!C7
A11: ='План работ'!C8
A12: ='План работ'!C9
A13: ='План работ'!C10
A14: ='План работ'!C11
A15: ='План работ'!C12
A16: ='План работ'!C13
... A26: ='План работ'!C23

Sheet Бриф
A1: БРИФ ТАРГЕТОЛОГУ — MainExperts, Поток 2
A2: =CONCATENATE("Кампания: ",Паспорт!B4," · Статус: ",Паспорт!B18," · Оффер: ",Паспорт!B8)
A3: =CONCATENATE("Шаг после квиза: ",Паспорт!B9," (дата решения: ",TEXT(Паспорт!B10,"DD.MM.YYYY"),")")
A5: 1. ДОСТУПЫ: кабинеты VK [заполнить], Meta [заполнить]; пиксели [заполнить]; Метрика/GA/Data Studio [заполнить]
A6: 2. UTM: https://mainexperts.online/[посадочная]?utm_source={vk|meta}&utm_medium=cpc&utm_campaign=[название]&utm_content={креатив}&utm_term={аудитория}. Домен .ru с Meta не работает — только mainexperts.online (канон).
A7: =CONCATENATE("3. ЯЧЕЙКИ: ",Паспорт!B6," — бюджет ",Паспорт!B12," $; ",Паспорт!B7," — бюджет ",Паспорт!B13," $. Минимум 400 $ на ячейку — внутренний норматив.")
A8: Аудитория: родители 38–50 (персонажи кастдева); развилка «родитель/подросток» не закрыта — закупка на родителя. Исключения: [заполнить]
A9: 4. ФОРМАТЫ: истории + карусель (видео — следующий шаг); 5 слоганов под A/B, заглушка — «Определи будущее твоего ребёнка».
A10: ЗАПРЕЩЕНО: названия методик (нет лицензии — только рабочие переименования); ПДн детей; обещания гарантированного результата.
A11: =CONCATENATE("5. СТОП-ПРАВИЛА: расход без лида до стопа ",Измерения!B10," $; потолок CPL ",Измерения!B9," $; мин. выборка ",Измерения!B11," лидов; ключевой KPI — ДРР, цель ",Паспорт!B15," %.")
A12: Порядок разбора отклонений: кампания → креатив → аудитория → посадочная.
A13: 6. МАРКИРОВКА/ПОЛИТИКИ: РФ — ОРД + erid на каждый креатив; площадки — категория «дети», обещания результата, здоровье.
A14: =CONCATENATE("7. ОТЧЁТНОСТЬ: ",Измерения!B12,". Формат: расход, показы, клики, CPL, лиды, шаги квиза, оплаты, ДРР по ячейке. Данные Потока 1 не включаются.")
A15: 8. КОНТАКТНЫЕ ТОЧКИ (без имён): таргет · посадочная · аналитика · платежи · методология · юридическое · владелец кампании
A16: Гипотеза кампании не валидирована — кампания и есть её проверка.

Sheet Чек-лист
A1: =IF(COUNTIF(B4:B12,"да")=9,"✓ ГОТОВ К ЗАПУСКУ — все «да»","■ ЗАПУСК ЗАПРЕЩЁН — "&COUNTIF(B4:B12,"да")&" из 9 «да»")
A2: Правило: без всех «да» запуск запрещён.
A3: Пункт | B3: Да/Нет
A4: Методология скрининга принята (блокер №1 канона) | B4: нет
A5: Профиль после скрининга не пустой (продуктовый блокер) | B5: нет
A6: Квиз проходится с телефона за целевое время | B6: нет
A7: События летят насквозь до оплаты | B7: нет
A8: Тестовая транзакция Robokassa прошла | B8: нет
A9: Оферта и согласия на посадочной | B9: нет
A10: Маркировка (ОРД, erid) настроена | B10: нет
A11: Стоп-правила согласованы | B11: нет
A12: Выбор флоу (оплата до/после скрининга) зафиксирован с датой | B12: нет

Sheet Риски
A1: Риск | B1: Вероятность | C1: Эффект | D1: Действие | E1: Триггер
A2: Юридический: данные несовершеннолетних, согласие родителя | B2: средняя | C2: высокий | D2: возрастная логика; согласие; минимизация ПДн детей | E2: жалоба / претензия / блок площадки
A3: Продуктовый: пустой профиль после скрининга | B3: высокая | C3: высокий | D3: не запускать до закрытия блокера (чек-лист) | E3: тест прохождения квиза
A4: Аналитический: разрывы атрибуции; ограничения Meta по iOS | B4: высокая | C4: средний | D4: ручное сведение оплат с источником; окно атрибуции | E4: расхождение платёжки и кабинета
A5: Платёжный: отклонение карт; комиссия 10% | B5: средняя | C5: средний | D5: тестовые транзакции; Stripe — параллельно, не блокер | E5: доля отклонённых оплат
A6: Модерация площадок: категория «дети», обещания результата | B6: средняя | C6: средний | D6: тексты без запрещённых обещаний; запас креативов | E6: реджект кампании
A7: Гео/валютные ограничения MENA | B7: средняя | C7: средний | D7: проверка оплат из MENA до масштабирования | E7: провал оплат по гео
A8: Центральная гипотеза не валидирована | B8: — | C8: критический | D8: кампания = проверка; трактовать результат как тест | E8: конверсия скрининг→оплата

Sheet Измерения
A1: Цепочка событий (вебинарная ячейка = другая цепочка):
A2: Показ | B2: Клик | C2: Открытие квиза | D2: Старт квиза | E2: Шаги квиза (отвал по шагам) | F2: Завершение квиза | G2: Контакт (e-mail до результата) | H2: Целевое действие | I2: Оплата
A4: Формулы:
A5: ДРР = расход ÷ выручка кампании × 100% (ключевой KPI)
A6: CPL = расход ÷ лиды (прокси)
A7: Конверсия шага = следующий шаг ÷ предыдущий; выручка — только оплаты Потока 2, атрибутированные кампании (сведение вручную)
A8: Порог решения | B8: Значение | C8: Комментарий
A9: Потолок CPL, $ | C9: стоп связки при превышении на выборке
A10: Расход без лида до стопа, $ | C10: стоп-правило
A11: Мин. выборка до решения, лидов | C11: до неё решений не принимать
A12: Частота отчёта таргетолога | B12: 2 раза в неделю | C12: в бриф
A13: Окно атрибуции, дней | C13: зафиксировать до первого прогона
A16: Решения по порогам: стоп → правка → масштабирование. Порядок разбора отклонений: кампания → креатив → аудитория → посадочная. ДАННЫЕ ПОТОКА 1 В ОТЧЁТЫ КАМПАНИИ НЕ ПОПАДАЮТ.
