Workbook

Sheet Дашборд компании
A1: 🏢 Дашборд компании MainExperts — цель, воронка, P&L (план / факт)
A2: Все числа считаются формулами от листа «Параметры» (курс $ = 80). Синее — входные данные, жёлтое — ваш факт.
A4: 🎯 ЦЕЛЬ КОМПАНИИ
A5: Показатель | B5: Значение
A6: Цель, $ | B6: =Параметры!$B$24
A7: Цель, ₽ (× курс) | B7: =Параметры!$B$24*Параметры!$B$3
A8: Цель в месяц, ₽ | B8: =B7/Параметры!$B$25
A9: Выручка / цикл (план, компания) | B9: ='P&L компании'!F5
A10: Накопленная выручка (факт) ✎
A11: % достижения цели (факт) | B11: =B10/B7
A12: Продаж 50К для цели (если только 50К) | B12: =B7/Параметры!$B$12
A13: …в день (× горизонт) | B13: =B12/(Параметры!$B$25*30)
A14: Потолок ручной проверки отчёта ≈ 9–10/день — выше этого цель упирается в узкое место (этап 5).
A16: 📌 KPI ЦИКЛА ($2000: 1000 VK + 1000 Meta)
A17: Метрика | B17: План | C17: Факт | D17: Δ (факт−план) | E17: Светофор/примечание
A18: Рекламный бюджет, ₽ | B18: =Маркетинг!D3 | D18: =C18-B18 | E18: вход = $2000 × курс
A19: Лиды (скрининги, e-mail) | B19: =Маркетинг!D6 | D19: =C19-B19 | E19: реальный актив бюджета
A20: CPL, $ | B20: =Маркетинг!D7 | D20: =C20-B20
A21: Продажи 50К | B21: =Маркетинг!D8 | D21: =C21-B21 | E21: ⚠ ставка на гипотезу скрининга
A22: Выручка, ₽ | B22: =Маркетинг!D11 | D22: =C22-B22
A23: ДРР | B23: =Маркетинг!D12 | D23: =C23-B23 | E23: 🟢<50 · 🟡50–100 · 🔴>100
A24: Операционный результат, ₽ | B24: ='P&L компании'!F10 | D24: =C24-B24 | E24: 🔴 < 0

Sheet Параметры
A1: ⚙ Параметры модели — редактируемые входные данные (синие ячейки)
A2: Показатель | B2: Значение | C2: Ед. / примечание
A3: Курс доллара | B3: 80 | C3: ₽ / $ — меняешь здесь, пересчитывается вся модель
A4: Бюджет VK | B4: 1000 | C4: $ за цикл
A5: Бюджет Meta | B5: 1000 | C5: $ за цикл
A6: CPC VK | B6: 0.34 | C6: $ за клик
A7: CPC Meta | B7: 0.675 | C7: $ за клик (диаспора/MENA дороже)
A8: Клик → старт скрининга, VK | B8: 0.4 | C8: доля
A9: Клик → старт скрининга, Meta | B9: 0.425 | C9: доля
A10: Старт → завершение скрининга | B10: 0.48 | C10: доля (≈18 вопросов + e-mail до результата)
A11: Завершивший → покупка 50К ⚠СТАВКА | B11: 0.003 | C11: доля — гипотеза скрининга, НЕ валидирована
A12: Цена «Профориентация 50К» | B12: 50000 | C12: ₽ — живой CTA Потока 2
A13: Цена подписки Pro | B13: 2990 | C13: ₽ / мес
A14: Цена подписки Ultima | B14: 9990 | C14: ₽ / мес
... A25: Горизонт цели | B25: 6 | C25: мес

Sheet Маркетинг
A1: 📊 Маркетинговый борт — воронка Потока 2, план / факт
A2: Показатель | B2: VK план | C2: Meta план | D2: Итого план | E2: VK факт | F2: Meta факт | G2: Итого факт | H2: Δ Итого (факт−план)
A3: Бюджет, ₽ | B3: =Параметры!$B$4*Параметры!$B$3 | C3: =Параметры!$B$5*Параметры!$B$3 | D3: =B3+C3 | H3: =G3-D3
A4: Клики | B4: =Параметры!$B$4/Параметры!$B$6 | C4: =Параметры!$B$5/Параметры!$B$7 | D4: =B4+C4 | H4: =G4-D4
A5: Старты скрининга | B5: =B4*Параметры!$B$8 | C5: =C4*Параметры!$B$9 | D5: =B5+C5 | H5: =G5-D5
A6: Завершённые скрининги = лиды (e-mail) | B6: =B5*Параметры!$B$10 | C6: =C5*Параметры!$B$10 | D6: =B6+C6 | H6: =G6-D6
A7: CPL, $ | B7: =Параметры!$B$4/B6 | C7: =Параметры!$B$5/C6 | D7: =(Параметры!$B$4+Параметры!$B$5)/D6 | H7: =G7-D7
A8: Продажи «Профориентация 50К» ⚠СТАВКА | B8: =B6*Параметры!$B$11 | C8: =C6*Параметры!$B$11 | D8: =B8+C8 | H8: =G8-D8
A9: Выручка 50К, ₽ | B9: =B8*Параметры!$B$12 | C9: =C8*Параметры!$B$12 | D9: =B9+C9 | H9: =G9-D9
A10: Выручка подписок, ₽ | D10: =Параметры!$B$15*Параметры!$B$13+Параметры!$B$16*Параметры!$B$14 | H10: =G10-D10
A11: Выручка всего, ₽ | B11: =B9 | C11: =C9 | D11: =D9+D10 | H11: =G11-D11
A12: ДРР (реклама ₽ / выручка ₽) | B12: =B3/B11 | C12: =C3/C11 | D12: =D3/D11 | H12: =G12-D12
A14: Жёлтые ячейки «факт» — для ваших фактических чисел; Δ считается автоматически. ДРР: 🟢<50% · 🟡50–100% · 🔴>100%. «Продажи 50К» дробные — матожидание, фактический исход цикла 0–3.

Sheet Контент-атрибуция
A1: 🧭 Контент-атрибуция — какая статья / тема / канал → продажи и ДРР (факт)
A2: Статья / URL | B2: Тема | C2: Слов | D2: Канал | E2: UTM | F2: Показы | G2: Клики | H2: Лиды | I2: CPL, $ | J2: Продажи 50К | K2: Выручка, ₽ | L2: Расход, ₽ | M2: ДРР | N2: Свет.
A3: /blog/professii-buduschego | B3: Профессии будущего | C3: 1800 | D3: VK | E3: seo/prof-future | F3: 12400 | G3: 520 | H3: 210 | I3: =IF(H3=0,0,(L3/Параметры!$B$3)/H3) | J3: 1 | K3: 50000 | L3: 18000 | M3: =IF(K3=0,"",L3/K3)
A4: /lp/5-voprosov | B4: 5 вопросов о талантах (лид-магнит) | C4: 600 | D4: Meta | E4: meta/lm-5q | F4: 48000 | G4: 900 | H4: 540 | I4: =IF(H4=0,0,(L4/Параметры!$B$3)/H4) | J4: 1 | K4: 50000 | L4: 38000 | M4: =IF(K4=0,"",L4/K4)
A5: /lp/7-oshibok | B5: 7 ошибок родителей | C5: 900 | D5: VK | E5: vk/lm-7err | F5: 31000 | G5: 610 | H5: 380 | I5: =IF(H5=0,0,(L5/Параметры!$B$3)/H5) | J5: 0 | K5: 0 | L5: 16000 | M5: =IF(K5=0,"",L5/K5)
I6: =IF(H6=0,0,(L6/Параметры!$B$3)/H6) | M6: =IF(K6=0,"",L6/K6)
I7: =IF(H7=0,0,(L7/Параметры!$B$3)/H7) | M7: =IF(K7=0,"",L7/K7)
I8: =IF(H8=0,0,(L8/Параметры!$B$3)/H8) | M8: =IF(K8=0,"",L8/K8)
I9: =IF(H9=0,0,(L9/Параметры!$B$3)/H9) | M9: =IF(K9=0,"",L9/K9)
I10: =IF(H10=0,0,(L10/Параметры!$B$3)/H10) | M10: =IF(K10=0,"",L10/K10)
A11: ИТОГО / сводный ДРР | F11: =SUM(F3:F10) | G11: =SUM(G3:G10) | H11: =SUM(H3:H10) | J11: =SUM(J3:J10) | K11: =SUM(K3:K10) | L11: =SUM(L3:L10) | M11: =IF(K11=0,"",L11/K11)
A13: Жёлтые ячейки — ваш факт по кампаниям. CPL и ДРР считаются сами. Сводный ДРР внизу = Σрасход / Σвыручка. Три строки — пример, замени своими.

Sheet Юнит-экономика
A1: 💸 Юнит-экономика «Профориентация 50 000 ₽» (Поток 2)
A2: Показатель | B2: Значение | C2: Формула / примечание
A3: Цена | B3: =Параметры!$B$12 | C3: живой CTA Потока 2
A4: Переменные на сделку, ₽ | B4: =Параметры!$B$17*Параметры!$B$18+Параметры!$B$19+Параметры!$B$12*Параметры!$B$20 | C4: проверка эксперта + ИИ + эквайринг
A5: CM (вклад на сделку), ₽ | B5: =B3-B4 | C5: цена − переменные
A6: CM, % | B6: =B5/B3
A7: CM на человеко-час эксперта, ₽/ч | B7: =B5/Параметры!$B$17 | C7: цена узкого места (этап 5)
A8: Постоянные за цикл, ₽ | B8: =Параметры!$B$21*Параметры!$B$3+Параметры!$B$22*Параметры!$B$3+Параметры!$B$23 | C8: Meta-спец + инструменты + накладные
A9: Реклама за цикл, ₽ | B9: =(Параметры!$B$4+Параметры!$B$5)*Параметры!$B$3
A10: Безубыточность (покрыть постоянные), сделок | B10: =B8/B5
A11: Безубыточность (реклама + постоянные), сделок | B11: =(B9+B8)/B5 | C11: сколько продаж 50К нужно «в плюс»

Sheet P&L компании
A1: 📈 P&L компании — план / факт, потоки раздельно
A2: Статья, ₽ | B2: Поток 2 план | C2: Поток 2 факт | D2: Поток 1 план | E2: Поток 1 факт | F2: Компания план | G2: Компания факт
A3: Выручка 50К / профориентация | B3: =Маркетинг!D9 | F3: =B3+D3 | G3: =C3+E3
A4: Выручка подписок | B4: =Маркетинг!D10 | F4: =B4+D4 | G4: =C4+E4
A5: Выручка ИТОГО | B5: =B3+B4 | F5: =B5+D5 | G5: =C5+E5
A6: − Реклама | B6: =-(Параметры!$B$4+Параметры!$B$5)*Параметры!$B$3 | F6: =B6+D6 | G6: =C6+E6
A7: − Переменные (по проданным отчётам) | B7: =-Маркетинг!D8*'Юнит-экономика'!B4 | F7: =B7+D7 | G7: =C7+E7
A8: =Контрибуция | B8: =B5+B6+B7 | F8: =B8+D8 | G8: =C8+E8
A9: − Постоянные | B9: =-('Юнит-экономика'!B8) | F9: =B9+D9 | G9: =C9+E9
A10: =Операционный результат | B10: =B8+B9 | F10: =B10+D10 | G10: =C10+E10
A11: ДРР (реклама / выручка) | B11: =-B6/B5 | F11: =B11+D11 | G11: =C11+E11
A12: ROMI (опер. результат / реклама) | B12: =B10/-B6 | F12: =B12+D12 | G12: =C12+E12
A14: Поток 1 (HNW, личные продажи Макса) — жёлтые ячейки заполняются вручную, в воронку Потока 2 не входит. Жёлтое = ввод. 🔴 опер. результат < 0.
